ratelimiter.py
ratelimiter-1.2.0.dist-info/DESCRIPTION.rst
ratelimiter-1.2.0.dist-info/METADATA
ratelimiter-1.2.0.dist-info/RECORD
ratelimiter-1.2.0.dist-info/WHEEL
ratelimiter-1.2.0.dist-info/metadata.json
ratelimiter-1.2.0.dist-info/top_level.txt
