Metadata-Version: 1.1
Name: ratelimiter
Version: 1.2.0
Summary: Simple python rate limiting object
Home-page: https://github.com/RazerM/ratelimiter
Author: Frazer McLean
Author-email: frazer@frazermclean.co.uk
License: Apache
Platform: UNKNOWN
Classifier: Development Status :: 5 - Production/Stable
Classifier: License :: OSI Approved :: Apache Software License
